iot2mqtt/__init__.py
iot2mqtt/abstract.py
iot2mqtt/central.py
iot2mqtt/dev.py
iot2mqtt/encoder.py
iot2mqtt/exceptions.py
iot2mqtt/messenger.py
iot2mqtt/mqtthelper.py
iot2mqtt/processor.py
iot2mqtt/setup.py
iot2mqtt/topics.py
iot2mqtt/utils.py
iot2mqtt/version.py
iot2mqtt-0.17.1.data/scripts/cli_iot2mqtt
iot2mqtt-0.17.1.dist-info/licenses/LICENSE.txt
iot2mqtt-0.17.1.dist-info/METADATA
iot2mqtt-0.17.1.dist-info/WHEEL
iot2mqtt-0.17.1.dist-info/top_level.txt
iot2mqtt-0.17.1.dist-info/RECORD
