Metadata-Version: 2.4
Name: iot2mqtt
Version: 0.17.1
Summary: Simplifying IoT Solutions with MQTT Integration
Home-page: https://github.com/slassabe/iot2mqtt
Author: Serge LASSABE
Author-email: dev@lassabe.org
License: MIT
License-File: LICENSE.txt
Requires-Dist: paho-mqtt
Requires-Dist: certifi
Requires-Dist: requests
Requires-Dist: pydantic
Dynamic: author
Dynamic: author-email
Dynamic: description
Dynamic: description-content-type
Dynamic: home-page
Dynamic: license
Dynamic: license-file
Dynamic: requires-dist
Dynamic: summary
